[
    {
        "id":1,
        "name": "jhon",
        "phone":"12348917436",
        "email":"jhon@gmail.com",
        "photo":"http://placekitten.com/500"
    },
    {
        "id": 2,
        "name": "alex",
        "phone":"12348917436",
        "email":"jhon@gmail.com",
        "photo":"http://placekitten.com/500"
    },
    {
        "id": 3,
        "name": "mikhael",
        "phone":"12348917436",
        "email":"jhon@gmail.com",
        "photo":"http://placekitten.com/500"
    },
    {
        "id": 4,
        "name": "rozalia",
        "phone":"12348917436",
        "email":"jhon@gmail.com",
        "photo":"http://placekitten.com/500"
    }
]